videoutils/__init__.py
videoutils/_nbdev.py
videoutils/io.py
videoutils/utils.py
videoutils-0.0.35.dist-info/LICENSE
videoutils-0.0.35.dist-info/METADATA
videoutils-0.0.35.dist-info/WHEEL
videoutils-0.0.35.dist-info/entry_points.txt
videoutils-0.0.35.dist-info/top_level.txt
videoutils-0.0.35.dist-info/RECORD
