Metadata-Version: 2.1
Name: videoutils
Version: 0.0.35
Summary: OpenCV utilities for reading video frames
Home-page: https://github.com/rsomani95/videoutils
Author: Rahul Somani
Author-email: rsomani95@gmail.com
License: Apache Software License 2.0
Keywords: cv2 openCV video utilities read helper data
Platform: UNKNOWN
Classifier: Development Status :: 3 - Alpha
Classifier: Intended Audience :: Developers
Classifier: License :: OSI Approved :: Apache Software License
Classifier: Natural Language :: English
Classifier: Programming Language :: Python :: 3.6
Classifier: Programming Language :: Python :: 3.7
Classifier: Programming Language :: Python :: 3.8
Requires-Python: >=3.6
